EasyVision/__init__.py
EasyVision/__init__.pyc
EasyVision/base.py
EasyVision/base.pyc
EasyVision/exceptions.py
EasyVision/exceptions.pyc
EasyVision/processorstackbuilder.py
EasyVision/processorstackbuilder.pyc
EasyVision/server.py
EasyVision/server.pyc
EasyVision/bin/__init__.py
EasyVision/bin/__init__.pyc
EasyVision/bin/calibrate_camera.py
EasyVision/bin/calibrate_camera.pyc
EasyVision/bin/calibrate_stereo.py
EasyVision/bin/calibrate_stereo.pyc
EasyVision/bin/client.py
EasyVision/bin/client.pyc
EasyVision/bin/learn_histogram.py
EasyVision/bin/learn_histogram.pyc
EasyVision/bin/learn_model.py
EasyVision/bin/learn_model.pyc
EasyVision/bin/mp.py
EasyVision/bin/mp.pyc
EasyVision/bin/performance_mp.py
EasyVision/bin/performance_mp.pyc
EasyVision/bin/performance_mp_stereo_calibrated.py
EasyVision/bin/performance_mp_stereo_calibrated.pyc
EasyVision/bin/performance_visualodometry2d.py
EasyVision/bin/performance_visualodometry2d.pyc
EasyVision/bin/performance_visualodometry3d2d.py
EasyVision/bin/performance_visualodometry3d2d.pyc
EasyVision/bin/performance_visualodometry_stereo.py
EasyVision/bin/performance_visualodometry_stereo.pyc
EasyVision/bin/server.py
EasyVision/bin/server.pyc
EasyVision/docs/__init__.py
EasyVision/docs/__init__.pyc
EasyVision/engine/__init__.py
EasyVision/engine/__init__.pyc
EasyVision/engine/base.py
EasyVision/engine/base.pyc
EasyVision/engine/bowvocabulary.py
EasyVision/engine/bowvocabulary.pyc
EasyVision/engine/objectrecognition.py
EasyVision/engine/objectrecognition.pyc
EasyVision/engine/occupancygridmap.py
EasyVision/engine/occupancygridmap.pyc
EasyVision/engine/orbvoc.dbow3
EasyVision/engine/visualodometry_2d.py
EasyVision/engine/visualodometry_2d.pyc
EasyVision/engine/visualodometry_3d2d.py
EasyVision/engine/visualodometry_3d2d.pyc
EasyVision/engine/visualodometry_stereo.py
EasyVision/engine/visualodometry_stereo.pyc
EasyVision/models/__init__.py
EasyVision/models/__init__.pyc
EasyVision/models/base.py
EasyVision/models/base.pyc
EasyVision-0.0.3.dist-info/AUTHORS.rst
EasyVision-0.0.3.dist-info/LICENSE
EasyVision-0.0.3.dist-info/LICENSE.txt
EasyVision-0.0.3.dist-info/METADATA
EasyVision-0.0.3.dist-info/WHEEL
EasyVision-0.0.3.dist-info/top_level.txt
EasyVision-0.0.3.dist-info/RECORD
