Metadata-Version: 2.1
Name: EasyVision
Version: 0.0.3
Summary: Easy Computer Vision Library using OpenCV.
Home-page: https://github.com/FoxIS/
Author: Andrius Mikonis
Author-email: andrius.mikonis@gmail.com
Maintainer: Andrius Mikonis
Maintainer-email: andrius.mikonis@gmail.com
License: BSD 3-Clause
Download-URL: https://pypi.python.org/pypi/EasyVision/0.0.3#downloads
Platform: Windows
Platform: MacOS
Platform: Unix
Classifier: Development Status :: 4 - Beta
Classifier: Intended Audience :: Developers
Classifier: License :: OSI Approved :: MIT License
Classifier: Natural Language :: English
Classifier: Operating System :: Microsoft :: Windows
Classifier: Operating System :: MacOS
Classifier: Operating System :: Unix
Classifier: Programming Language :: Python
Classifier: Programming Language :: Python :: 2.7
Classifier: Programming Language :: Python :: 3.5
Classifier: Programming Language :: Python :: 3.6
Classifier: Programming Language :: Python :: 3.7
Requires-Dist: numpy (==1.15.4)
Requires-Dist: opencv-contrib-python (==3.4.2.16)
Requires-Dist: pyro4 (>=4.75)
Provides-Extra: docs
Requires-Dist: sphinx (==1.8.1) ; extra == 'docs'
Requires-Dist: sphinx-rtd-theme ; extra == 'docs'
Requires-Dist: sphinx-jinja ; extra == 'docs'
Requires-Dist: sphinx-copybutton ; extra == 'docs'
Requires-Dist: docfly (>=0.0.16) ; extra == 'docs'
Requires-Dist: rstobj ; extra == 'docs'
Requires-Dist: pygments ; extra == 'docs'
Provides-Extra: tests
Requires-Dist: pytest (>=3.2.3) ; extra == 'tests'
Requires-Dist: pytest-mock (>=1.10.0) ; extra == 'tests'
Requires-Dist: pytest-cov (<2.6.0) ; extra == 'tests'
Requires-Dist: numpy (==1.15.4) ; extra == 'tests'
Requires-Dist: opencv-contrib-python (==3.4.2.16) ; extra == 'tests'
Requires-Dist: pyro4 (>=4.75) ; extra == 'tests'
